AstroSpace/.dockerignore
AstroSpace/__init__.py
AstroSpace/auth.py
AstroSpace/blog.py
AstroSpace/config.py
AstroSpace/db.py
AstroSpace/package-lock.json
AstroSpace/package.json
AstroSpace/schema.sql
AstroSpace/tailwind.config.js
AstroSpace/static/input.css
AstroSpace/static/styles.css
AstroSpace/static/assets/images/Main_Image.jpg
AstroSpace/static/assets/images/moon.png
AstroSpace/static/assets/images/pixinsight-140x40-black.en.png
AstroSpace/static/fonts/Lato-Black.ttf
AstroSpace/static/fonts/Lato-BlackItalic.ttf
AstroSpace/static/fonts/Lato-Bold.ttf
AstroSpace/static/fonts/Lato-BoldItalic.ttf
AstroSpace/static/fonts/Lato-Hairline.ttf
AstroSpace/static/fonts/Lato-HairlineItalic.ttf
AstroSpace/static/fonts/Lato-Heavy.ttf
AstroSpace/static/fonts/Lato-HeavyItalic.ttf
AstroSpace/static/fonts/Lato-Italic.ttf
AstroSpace/static/fonts/Lato-Light.ttf
AstroSpace/static/fonts/Lato-LightItalic.ttf
AstroSpace/static/fonts/Lato-Medium.ttf
AstroSpace/static/fonts/Lato-MediumItalic.ttf
AstroSpace/static/fonts/Lato-Regular.ttf
AstroSpace/static/fonts/Lato-Semibold.ttf
AstroSpace/static/fonts/Lato-SemiboldItalic.ttf
AstroSpace/static/fonts/Lato-Thin.ttf
AstroSpace/static/fonts/Lato-ThinItalic.ttf
AstroSpace/static/fonts/Patung-Zpeax.ttf
AstroSpace/static/fonts/Scribble.woff2
AstroSpace/templates/base.html
AstroSpace/templates/collection.html
AstroSpace/templates/create.html
AstroSpace/templates/create_blog.html
AstroSpace/templates/home.html
AstroSpace/templates/image_detail.html
AstroSpace/templates/user_posts.html
AstroSpace/templates/auth/auth.html
AstroSpace/utils/__init__.py
AstroSpace/utils/blog_form.py
AstroSpace/utils/moon_phase.py
AstroSpace/utils/phd2logparser.py
AstroSpace/utils/platesolve.py
AstroSpace/utils/queries.py
AstroSpace/utils/simbad_object_description.json
AstroSpace/utils/utils.py
AstroSpace/utils/xisf_reader.py
astrospace-1.0.3.dist-info/METADATA
astrospace-1.0.3.dist-info/WHEEL
astrospace-1.0.3.dist-info/licenses/LICENSE
astrospace-1.0.3.dist-info/RECORD
