Metadata-Version: 2.4
Name: astrospace
Version: 1.0.3
Summary: A Flask-based astrophotography web application
Author-email: Sharon Shaji <sharonshaji92@outlook.com>
License-File: LICENSE
Requires-Python: >=3.11
Requires-Dist: astropy
Requires-Dist: astroquery
Requires-Dist: bokeh==3.7.3
Requires-Dist: ephem
Requires-Dist: flask
Requires-Dist: flask-login
Requires-Dist: flask-wtf
Requires-Dist: numpy
Requires-Dist: pandas
Requires-Dist: photoutils
Requires-Dist: pillow
Requires-Dist: psycopg2-binary
Requires-Dist: requests
Requires-Dist: xisf
